{"end_date":"2026-05-15","hourly_average_occupied":{"00:00":0.0,"01:00":0.0,"02:00":0.0,"03:00":0.0,"04:00":0.0,"05:00":0.0,"06:00":0.0,"07:00":0.123,"08:00":0.297,"09:00":0.386,"10:00":0.452,"11:00":0.58,"12:00":0.624,"13:00":0.262,"14:00":0.353,"15:00":0.46,"16:00":0.636,"17:00":0.439,"18:00":0.368,"19:00":0.365,"20:00":0.375,"21:00":0.62,"22:00":0.587,"23:00":0.255},"included_days":7,"metric":"Mean occupied EVSEs per local hour. Unknown or missing status is not counted as occupied; one primary provider is selected per station to avoid duplicate provider mappings.","provider_uids":["eround"],"requested_days":7,"start_date":"2026-05-09","station":{"address":"Werner-von-Siemens-Str. 4 89415 Lauingen Landkreis Dillingen a.d. Donau","charging_points_count":2,"city":"Lauingen","max_power_kw":150.0,"operator":"EWE Go GmbH","postcode":"89415","station_id":"0ff3913aa9595824"},"station_id":"0ff3913aa9595824","timezone":"Europe/Berlin"}