{"end_date":"2026-05-13","hourly_average_occupied":{"00:00":0.06,"01:00":0.162,"02:00":0.286,"03:00":0.286,"04:00":0.286,"05:00":0.286,"06:00":0.35,"07:00":0.559,"08:00":0.571,"09:00":0.571,"10:00":0.598,"11:00":0.714,"12:00":0.756,"13:00":1.027,"14:00":1.288,"15:00":1.429,"16:00":1.48,"17:00":1.571,"18:00":1.539,"19:00":1.838,"20:00":1.901,"21:00":1.929,"22:00":1.714,"23:00":1.714},"included_days":7,"metric":"Mean occupied EVSEs per local hour. Unknown or missing status is not counted as occupied; one primary provider is selected per station to avoid duplicate provider mappings.","provider_uids":["tesla"],"requested_days":7,"start_date":"2026-05-07","station":{"address":"Frankenring 13 96237 Ebersdorf b. Coburg Landkreis Coburg","charging_points_count":8,"city":"Ebersdorf b. Coburg","max_power_kw":250.0,"operator":"Tesla Germany GmbH","postcode":"96237","station_id":"1a6567ab14d32a24"},"station_id":"1a6567ab14d32a24","timezone":"Europe/Berlin"}