{"end_date":"2026-05-12","hourly_average_occupied":{"00:00":0.013,"01:00":0.0,"02:00":0.0,"03:00":0.0,"04:00":0.0,"05:00":0.009,"06:00":0.0,"07:00":0.048,"08:00":0.278,"09:00":0.696,"10:00":1.231,"11:00":0.631,"12:00":0.21,"13:00":0.526,"14:00":0.432,"15:00":0.995,"16:00":0.845,"17:00":0.633,"18:00":0.798,"19:00":0.493,"20:00":0.563,"21:00":0.324,"22:00":0.144,"23:00":0.143},"included_days":7,"metric":"Mean occupied EVSEs per local hour. Unknown or missing status is not counted as occupied; one primary provider is selected per station to avoid duplicate provider mappings.","provider_uids":["enbwmobility"],"requested_days":7,"start_date":"2026-05-06","station":{"address":"Burgdorfer Straße 23 31311 Uetze Landkreis Region Hannover","charging_points_count":4,"city":"Uetze","max_power_kw":100.0,"operator":"EnBW mobility+ AG und Co.KG","postcode":"31311","station_id":"261c6f0610403f1a"},"station_id":"261c6f0610403f1a","timezone":"Europe/Berlin"}