{"end_date":"2026-05-15","hourly_average_occupied":{"00:00":0.046,"01:00":0.0,"02:00":0.043,"03:00":0.103,"04:00":0.392,"05:00":1.259,"06:00":0.904,"07:00":0.725,"08:00":0.72,"09:00":0.658,"10:00":1.103,"11:00":1.009,"12:00":1.003,"13:00":1.385,"14:00":1.108,"15:00":0.987,"16:00":1.421,"17:00":1.688,"18:00":1.214,"19:00":1.153,"20:00":1.011,"21:00":1.074,"22:00":0.413,"23:00":0.542},"included_days":7,"metric":"Mean occupied EVSEs per local hour. Unknown or missing status is not counted as occupied; one primary provider is selected per station to avoid duplicate provider mappings.","provider_uids":["eround"],"requested_days":7,"start_date":"2026-05-09","station":{"address":"Rudolf-Diesel-Str. 2 26670 Uplengen Landkreis Leer","charging_points_count":4,"city":"Uplengen","max_power_kw":400.0,"operator":"EWE Go GmbH","postcode":"26670","station_id":"3c946a8ac8a5fc81"},"station_id":"3c946a8ac8a5fc81","timezone":"Europe/Berlin"}