{"end_date":"2026-05-15","hourly_average_occupied":{"00:00":0.0,"01:00":0.0,"02:00":0.0,"03:00":0.0,"04:00":0.0,"05:00":0.0,"06:00":0.0,"07:00":0.166,"08:00":0.206,"09:00":0.146,"10:00":0.165,"11:00":0.017,"12:00":0.067,"13:00":0.031,"14:00":0.007,"15:00":0.05,"16:00":0.234,"17:00":0.067,"18:00":0.143,"19:00":0.089,"20:00":0.057,"21:00":0.0,"22:00":0.0,"23:00":0.0},"included_days":7,"metric":"Mean occupied EVSEs per local hour. Unknown or missing status is not counted as occupied; one primary provider is selected per station to avoid duplicate provider mappings.","provider_uids":["vaylens"],"requested_days":7,"start_date":"2026-05-09","station":{"address":"Aichacher Straße 15 86674 Baar Landkreis Aichach-Friedberg","charging_points_count":3,"city":"Baar","max_power_kw":50.0,"operator":"Autohaus Kürbis GmbH","postcode":"86674","station_id":"5f0345712f85d574"},"station_id":"5f0345712f85d574","timezone":"Europe/Berlin"}