{"end_date":"2026-05-16","hourly_average_occupied":{"00:00":0.0,"01:00":0.036,"02:00":0.0,"03:00":0.0,"04:00":0.0,"05:00":0.0,"06:00":0.0,"07:00":0.0,"08:00":0.059,"09:00":0.071,"10:00":0.155,"11:00":0.273,"12:00":0.274,"13:00":0.095,"14:00":0.179,"15:00":0.202,"16:00":0.298,"17:00":0.203,"18:00":0.238,"19:00":0.393,"20:00":0.238,"21:00":0.072,"22:00":0.048,"23:00":0.119},"included_days":7,"metric":"Mean occupied EVSEs per local hour. Unknown or missing status is not counted as occupied; one primary provider is selected per station to avoid duplicate provider mappings.","provider_uids":["ladenetz_de_ladestationsdaten"],"requested_days":7,"start_date":"2026-05-10","station":{"address":"Marktplatz 7 87647 Unterthingau Landkreis Ostallgäu","charging_points_count":2,"city":"Unterthingau","max_power_kw":200.0,"operator":"energie schwaben gmbh","postcode":"87647","station_id":"7990f41907b287c1"},"station_id":"7990f41907b287c1","timezone":"Europe/Berlin"}