{"end_date":"2026-05-16","hourly_average_occupied":{"00:00":0.0,"01:00":0.055,"02:00":0.029,"03:00":0.096,"04:00":0.049,"05:00":0.09,"06:00":0.0,"07:00":0.228,"08:00":0.376,"09:00":0.769,"10:00":0.532,"11:00":0.772,"12:00":0.751,"13:00":1.024,"14:00":0.786,"15:00":0.712,"16:00":0.416,"17:00":0.572,"18:00":0.517,"19:00":0.511,"20:00":0.579,"21:00":0.411,"22:00":0.462,"23:00":0.204},"included_days":7,"metric":"Mean occupied EVSEs per local hour. Unknown or missing status is not counted as occupied; one primary provider is selected per station to avoid duplicate provider mappings.","provider_uids":["eco_movement"],"requested_days":7,"start_date":"2026-05-10","station":{"address":"Erlenstegenstr. 39 49491 Nürnberg Kreisfreie Stadt Nürnberg","charging_points_count":8,"city":"Nürnberg","max_power_kw":300.0,"operator":"Shell Deutschland GmbH","postcode":"49491","station_id":"7e54f3f533ab8032"},"station_id":"7e54f3f533ab8032","timezone":"Europe/Berlin"}