{"end_date":"2026-05-10","hourly_average_occupied":{"00:00":0.007,"01:00":0.008,"02:00":0.0,"03:00":0.0,"04:00":0.0,"05:00":0.0,"06:00":0.0,"07:00":0.009,"08:00":0.088,"09:00":0.039,"10:00":0.518,"11:00":0.542,"12:00":0.274,"13:00":0.271,"14:00":0.569,"15:00":0.309,"16:00":0.232,"17:00":0.698,"18:00":0.777,"19:00":0.29,"20:00":0.16,"21:00":0.185,"22:00":0.143,"23:00":0.199},"included_days":7,"metric":"Mean occupied EVSEs per local hour. Unknown or missing status is not counted as occupied; one primary provider is selected per station to avoid duplicate provider mappings.","provider_uids":["eround"],"requested_days":7,"start_date":"2026-05-04","station":{"address":"Industriestr. 1 54634 Bitburg Landkreis Eifelkreis Bitburg-Prüm","charging_points_count":2,"city":"Bitburg","max_power_kw":300.0,"operator":"Pfalzwerke AG","postcode":"54634","station_id":"81e74f35ea3a0c31"},"station_id":"81e74f35ea3a0c31","timezone":"Europe/Berlin"}