{"end_date":"2026-05-15","hourly_average_occupied":{"00:00":0.0,"01:00":0.0,"02:00":0.0,"03:00":0.0,"04:00":0.0,"05:00":0.0,"06:00":0.0,"07:00":0.158,"08:00":0.116,"09:00":0.069,"10:00":0.486,"11:00":0.477,"12:00":0.553,"13:00":0.27,"14:00":0.644,"15:00":0.29,"16:00":0.248,"17:00":0.165,"18:00":0.158,"19:00":0.355,"20:00":0.461,"21:00":0.266,"22:00":0.059,"23:00":0.0},"included_days":7,"metric":"Mean occupied EVSEs per local hour. Unknown or missing status is not counted as occupied; one primary provider is selected per station to avoid duplicate provider mappings.","provider_uids":["vaylens"],"requested_days":7,"start_date":"2026-05-09","station":{"address":"Gänsrain 1 97769 Bad Brückenau Landkreis Bad Kissingen","charging_points_count":4,"city":"Bad Brückenau","max_power_kw":260.0,"operator":"Claus Heinemann Elektroanlagen GmbH","postcode":"97769","station_id":"87175619484df8d8"},"station_id":"87175619484df8d8","timezone":"Europe/Berlin"}