{"end_date":"2026-05-13","hourly_average_occupied":{"00:00":0.0,"01:00":0.0,"02:00":0.0,"03:00":0.0,"04:00":0.0,"05:00":0.0,"06:00":0.0,"07:00":0.0,"08:00":0.057,"09:00":0.033,"10:00":0.067,"11:00":0.013,"12:00":0.013,"13:00":0.064,"14:00":0.061,"15:00":0.097,"16:00":0.192,"17:00":0.12,"18:00":0.0,"19:00":0.0,"20:00":0.0,"21:00":0.006,"22:00":0.0,"23:00":0.0},"included_days":7,"metric":"Mean occupied EVSEs per local hour. Unknown or missing status is not counted as occupied; one primary provider is selected per station to avoid duplicate provider mappings.","provider_uids":["vaylens"],"requested_days":7,"start_date":"2026-05-07","station":{"address":"Am Sportplatz 6b 63791 Karlstein a. Main Landkreis Aschaffenburg","charging_points_count":2,"city":"Karlstein a. Main","max_power_kw":50.0,"operator":"ALDI SÜD Immobilienverwaltungs-GmbH & Co. oHG","postcode":"63791","station_id":"8e1c0a9e016991d2"},"station_id":"8e1c0a9e016991d2","timezone":"Europe/Berlin"}