{"end_date":"2026-05-13","hourly_average_occupied":{"00:00":0.052,"01:00":0.0,"02:00":0.0,"03:00":0.0,"04:00":0.0,"05:00":0.051,"06:00":0.0,"07:00":0.049,"08:00":0.019,"09:00":0.156,"10:00":0.074,"11:00":0.065,"12:00":0.092,"13:00":0.374,"14:00":0.2,"15:00":0.314,"16:00":0.347,"17:00":0.643,"18:00":0.238,"19:00":0.425,"20:00":0.565,"21:00":0.408,"22:00":0.422,"23:00":0.481},"included_days":7,"metric":"Mean occupied EVSEs per local hour. Unknown or missing status is not counted as occupied; one primary provider is selected per station to avoid duplicate provider mappings.","provider_uids":["eround"],"requested_days":7,"start_date":"2026-05-07","station":{"address":"Stiftsstr. 224 50171 Kerpen Kreis Rhein-Erft-Kreis","charging_points_count":2,"city":"Kerpen","max_power_kw":150.0,"operator":"EWE Go GmbH","postcode":"50171","station_id":"8fcfcbf47c443e6c"},"station_id":"8fcfcbf47c443e6c","timezone":"Europe/Berlin"}