{"end_date":"2026-05-11","hourly_average_occupied":{"00:00":0.003,"01:00":0.0,"02:00":0.0,"03:00":0.0,"04:00":0.0,"05:00":0.138,"06:00":0.286,"07:00":0.286,"08:00":0.286,"09:00":0.313,"10:00":0.474,"11:00":0.609,"12:00":0.722,"13:00":0.861,"14:00":0.744,"15:00":0.63,"16:00":0.667,"17:00":0.587,"18:00":0.397,"19:00":0.311,"20:00":0.429,"21:00":0.431,"22:00":0.384,"23:00":0.301},"included_days":7,"metric":"Mean occupied EVSEs per local hour. Unknown or missing status is not counted as occupied; one primary provider is selected per station to avoid duplicate provider mappings.","provider_uids":["vaylens"],"requested_days":7,"start_date":"2026-05-05","station":{"address":"Gottlieb-Daimler-Straße 10 54516 Wittlich Landkreis Bernkastel-Wittlich","charging_points_count":3,"city":"Wittlich","max_power_kw":125.0,"operator":"ALDI SÜD Immobilienverwaltungs-GmbH & Co. oHG","postcode":"54516","station_id":"94dd0bfa88dc6d59"},"station_id":"94dd0bfa88dc6d59","timezone":"Europe/Berlin"}