{"end_date":"2026-05-13","hourly_average_occupied":{"00:00":0.0,"01:00":0.0,"02:00":0.0,"03:00":0.0,"04:00":0.0,"05:00":0.073,"06:00":0.197,"07:00":0.286,"08:00":0.351,"09:00":0.22,"10:00":0.108,"11:00":0.319,"12:00":0.362,"13:00":0.803,"14:00":0.728,"15:00":0.352,"16:00":0.749,"17:00":0.879,"18:00":0.555,"19:00":0.408,"20:00":0.341,"21:00":0.386,"22:00":0.318,"23:00":0.396},"included_days":7,"metric":"Mean occupied EVSEs per local hour. Unknown or missing status is not counted as occupied; one primary provider is selected per station to avoid duplicate provider mappings.","provider_uids":["vaylens"],"requested_days":7,"start_date":"2026-05-07","station":{"address":"Kestnerstr. 33 30159 Hannover Landkreis Region Hannover","charging_points_count":2,"city":"Hannover","max_power_kw":75.0,"operator":"enercity AG","postcode":"30159","station_id":"968f770e683d9b76"},"station_id":"968f770e683d9b76","timezone":"Europe/Berlin"}