{"end_date":"2026-05-15","hourly_average_occupied":{"00:00":0.018,"01:00":0.067,"02:00":0.063,"03:00":0.0,"04:00":0.024,"05:00":0.0,"06:00":0.146,"07:00":0.203,"08:00":0.349,"09:00":0.47,"10:00":0.987,"11:00":1.501,"12:00":1.569,"13:00":1.271,"14:00":1.517,"15:00":1.259,"16:00":1.456,"17:00":1.321,"18:00":0.791,"19:00":0.582,"20:00":0.318,"21:00":0.059,"22:00":0.126,"23:00":0.164},"included_days":7,"metric":"Mean occupied EVSEs per local hour. Unknown or missing status is not counted as occupied; one primary provider is selected per station to avoid duplicate provider mappings.","provider_uids":["eco_movement"],"requested_days":7,"start_date":"2026-05-09","station":{"address":"Eifel West 0 54533 Niederöfflingen Landkreis Bernkastel-Wittlich","charging_points_count":6,"city":"Niederöfflingen","max_power_kw":350.0,"operator":"IONITY GmbH","postcode":"54533","station_id":"98b05f136b3fd57d"},"station_id":"98b05f136b3fd57d","timezone":"Europe/Berlin"}