{"end_date":"2026-05-13","hourly_average_occupied":{"00:00":0.0,"01:00":0.036,"02:00":0.096,"03:00":0.011,"04:00":0.0,"05:00":0.0,"06:00":0.111,"07:00":0.316,"08:00":0.275,"09:00":0.296,"10:00":0.451,"11:00":0.396,"12:00":0.568,"13:00":0.501,"14:00":0.847,"15:00":0.379,"16:00":0.592,"17:00":0.297,"18:00":0.633,"19:00":0.55,"20:00":0.143,"21:00":0.155,"22:00":0.093,"23:00":0.286},"included_days":7,"metric":"Mean occupied EVSEs per local hour. Unknown or missing status is not counted as occupied; one primary provider is selected per station to avoid duplicate provider mappings.","provider_uids":["eround"],"requested_days":7,"start_date":"2026-05-07","station":{"address":"Kaiserreich-Str. 2 83088 Kiefersfelden Landkreis Rosenheim","charging_points_count":2,"city":"Kiefersfelden","max_power_kw":150.0,"operator":"EWE Go GmbH","postcode":"83088","station_id":"9fd99d20903cc1af"},"station_id":"9fd99d20903cc1af","timezone":"Europe/Berlin"}