{"end_date":"2026-05-13","hourly_average_occupied":{"00:00":0.191,"01:00":0.585,"02:00":0.725,"03:00":0.747,"04:00":0.901,"05:00":0.865,"06:00":0.714,"07:00":0.793,"08:00":1.001,"09:00":0.836,"10:00":0.259,"11:00":0.447,"12:00":0.326,"13:00":0.257,"14:00":0.153,"15:00":0.298,"16:00":0.243,"17:00":0.308,"18:00":0.651,"19:00":0.267,"20:00":0.507,"21:00":0.206,"22:00":0.161,"23:00":0.284},"included_days":7,"metric":"Mean occupied EVSEs per local hour. Unknown or missing status is not counted as occupied; one primary provider is selected per station to avoid duplicate provider mappings.","provider_uids":["eco_movement"],"requested_days":7,"start_date":"2026-05-07","station":{"address":"Moerser Str. 121 47198 Duisburg Kreisfreie Stadt Duisburg","charging_points_count":4,"city":"Duisburg","max_power_kw":300.0,"operator":"Shell Deutschland GmbH","postcode":"47198","station_id":"c6024d5da8b58606"},"station_id":"c6024d5da8b58606","timezone":"Europe/Berlin"}