{"end_date":"2026-05-10","hourly_average_occupied":{"00:00":0.033,"01:00":0.0,"02:00":0.0,"03:00":0.0,"04:00":0.0,"05:00":0.0,"06:00":0.313,"07:00":0.348,"08:00":0.322,"09:00":0.286,"10:00":0.174,"11:00":0.143,"12:00":0.192,"13:00":0.185,"14:00":0.585,"15:00":0.691,"16:00":0.392,"17:00":0.633,"18:00":0.651,"19:00":0.285,"20:00":0.198,"21:00":0.255,"22:00":0.324,"23:00":0.291},"included_days":7,"metric":"Mean occupied EVSEs per local hour. Unknown or missing status is not counted as occupied; one primary provider is selected per station to avoid duplicate provider mappings.","provider_uids":["chargecloud"],"requested_days":7,"start_date":"2026-05-04","station":{"address":"Beethovenstraße 6 91074 Herzogenaurach Landkreis Erlangen-Höchstadt","charging_points_count":3,"city":"Herzogenaurach","max_power_kw":150.0,"operator":"Herzo Energie GmbH","postcode":"91074","station_id":"d0f34364bc0ef1b3"},"station_id":"d0f34364bc0ef1b3","timezone":"Europe/Berlin"}