{"end_date":"2026-05-15","hourly_average_occupied":{"00:00":0.0,"01:00":0.0,"02:00":0.0,"03:00":0.0,"04:00":0.0,"05:00":0.0,"06:00":0.0,"07:00":0.072,"08:00":0.446,"09:00":0.777,"10:00":0.845,"11:00":0.706,"12:00":0.503,"13:00":0.413,"14:00":0.607,"15:00":0.315,"16:00":0.404,"17:00":0.441,"18:00":0.339,"19:00":0.397,"20:00":0.356,"21:00":0.021,"22:00":0.0,"23:00":0.0},"included_days":7,"metric":"Mean occupied EVSEs per local hour. Unknown or missing status is not counted as occupied; one primary provider is selected per station to avoid duplicate provider mappings.","provider_uids":["vaylens"],"requested_days":7,"start_date":"2026-05-09","station":{"address":"Brahmsstr. 47 86368 Gersthofen Landkreis Augsburg","charging_points_count":2,"city":"Gersthofen","max_power_kw":150.0,"operator":"LEW Natur GmbH","postcode":"86368","station_id":"e31ae67f0a5953d8"},"station_id":"e31ae67f0a5953d8","timezone":"Europe/Berlin"}