{"end_date":"2026-05-13","hourly_average_occupied":{"00:00":0.0,"01:00":0.0,"02:00":0.0,"03:00":0.0,"04:00":0.006,"05:00":0.143,"06:00":0.079,"07:00":0.584,"08:00":0.542,"09:00":0.571,"10:00":0.664,"11:00":0.513,"12:00":0.508,"13:00":0.693,"14:00":0.711,"15:00":0.714,"16:00":0.561,"17:00":0.429,"18:00":0.429,"19:00":0.429,"20:00":0.511,"21:00":0.286,"22:00":0.286,"23:00":0.286},"included_days":7,"metric":"Mean occupied EVSEs per local hour. Unknown or missing status is not counted as occupied; one primary provider is selected per station to avoid duplicate provider mappings.","provider_uids":["monta"],"requested_days":7,"start_date":"2026-05-07","station":{"address":"Mühldorfer Straße 88 84503 Altötting Landkreis Altötting","charging_points_count":2,"city":"Altötting","max_power_kw":50.0,"operator":"VIOCON GmbH","postcode":"84503","station_id":"f56bc4f072f72601"},"station_id":"f56bc4f072f72601","timezone":"Europe/Berlin"}