{"end_date":"2026-05-15","hourly_average_occupied":{"00:00":0.297,"01:00":0.251,"02:00":0.297,"03:00":0.104,"04:00":0.143,"05:00":0.095,"06:00":0.115,"07:00":0.422,"08:00":0.625,"09:00":0.692,"10:00":0.595,"11:00":0.729,"12:00":1.265,"13:00":1.209,"14:00":1.161,"15:00":1.214,"16:00":0.973,"17:00":0.457,"18:00":0.633,"19:00":0.546,"20:00":0.279,"21:00":0.257,"22:00":0.078,"23:00":0.339},"included_days":7,"metric":"Mean occupied EVSEs per local hour. Unknown or missing status is not counted as occupied; one primary provider is selected per station to avoid duplicate provider mappings.","provider_uids":["eco_movement"],"requested_days":7,"start_date":"2026-05-09","station":{"address":"Reichsgrafenstr. 36 94036 Passau Kreisfreie Stadt Passau","charging_points_count":2,"city":"Passau","max_power_kw":350.0,"operator":"IONITY GmbH","postcode":"94036","station_id":"f5752ebe26137b70"},"station_id":"f5752ebe26137b70","timezone":"Europe/Berlin"}