{"end_date":"2026-05-14","hourly_average_occupied":{"00:00":0.0,"01:00":0.0,"02:00":0.0,"03:00":0.0,"04:00":0.0,"05:00":0.0,"06:00":0.0,"07:00":0.003,"08:00":0.236,"09:00":0.428,"10:00":0.418,"11:00":0.316,"12:00":0.413,"13:00":0.368,"14:00":0.229,"15:00":0.274,"16:00":0.465,"17:00":0.411,"18:00":0.323,"19:00":0.174,"20:00":0.143,"21:00":0.146,"22:00":0.143,"23:00":0.143},"included_days":7,"metric":"Mean occupied EVSEs per local hour. Unknown or missing status is not counted as occupied; one primary provider is selected per station to avoid duplicate provider mappings.","provider_uids":["vaylens"],"requested_days":7,"start_date":"2026-05-08","station":{"address":"Schiller Straße 109 63741 Aschaffenburg Kreisfreie Stadt Aschaffenburg","charging_points_count":2,"city":"Aschaffenburg","max_power_kw":300.0,"operator":"Numbat GmbH","postcode":"63741","station_id":"f7133c4922221adc"},"station_id":"f7133c4922221adc","timezone":"Europe/Berlin"}