{"end_date":"2026-05-14","hourly_average_occupied":{"00:00":0.105,"01:00":0.143,"02:00":0.143,"03:00":0.143,"04:00":0.203,"05:00":0.286,"06:00":0.286,"07:00":0.476,"08:00":0.632,"09:00":0.243,"10:00":0.11,"11:00":0.143,"12:00":0.297,"13:00":0.011,"14:00":0.054,"15:00":0.24,"16:00":0.46,"17:00":0.501,"18:00":0.189,"19:00":0.239,"20:00":0.331,"21:00":0.462,"22:00":0.429,"23:00":0.376},"included_days":7,"metric":"Mean occupied EVSEs per local hour. Unknown or missing status is not counted as occupied; one primary provider is selected per station to avoid duplicate provider mappings.","provider_uids":["vaylens"],"requested_days":7,"start_date":"2026-05-08","station":{"address":"Hüffertstraße 20 34414 Warburg Kreis Höxter","charging_points_count":2,"city":"Warburg","max_power_kw":50.0,"operator":"Stadtwerke Warburg GmbH","postcode":"34414","station_id":"fcfcf506b6f1ddd0"},"station_id":"fcfcf506b6f1ddd0","timezone":"Europe/Berlin"}