{"end_date":"2026-05-15","hourly_average_occupied":{"00:00":0.0,"01:00":0.0,"02:00":0.186,"03:00":0.143,"04:00":0.143,"05:00":0.143,"06:00":0.152,"07:00":0.486,"08:00":0.403,"09:00":0.286,"10:00":0.157,"11:00":0.172,"12:00":0.443,"13:00":0.39,"14:00":0.429,"15:00":0.468,"16:00":0.602,"17:00":0.599,"18:00":0.561,"19:00":0.571,"20:00":0.571,"21:00":0.834,"22:00":0.586,"23:00":0.187},"included_days":7,"metric":"Mean occupied EVSEs per local hour. Unknown or missing status is not counted as occupied; one primary provider is selected per station to avoid duplicate provider mappings.","provider_uids":["eround"],"requested_days":7,"start_date":"2026-05-09","station":{"address":"Schnackenburgallee 153 22525 Hamburg Kreisfreie Stadt Hamburg","charging_points_count":2,"city":"Hamburg","max_power_kw":150.0,"operator":"Hamburger Energiewerke Mobil GmbH","postcode":"22525","station_id":"feb51f9f56f8599f"},"station_id":"feb51f9f56f8599f","timezone":"Europe/Berlin"}