{"end_date":"2026-05-15","hourly_average_occupied":{"00:00":0.0,"01:00":0.0,"02:00":0.034,"03:00":0.0,"04:00":0.015,"05:00":0.143,"06:00":0.143,"07:00":0.238,"08:00":0.241,"09:00":0.722,"10:00":0.387,"11:00":0.425,"12:00":0.49,"13:00":0.713,"14:00":0.672,"15:00":0.402,"16:00":0.659,"17:00":0.559,"18:00":0.433,"19:00":0.438,"20:00":0.3,"21:00":0.287,"22:00":0.167,"23:00":0.234},"included_days":7,"metric":"Mean occupied EVSEs per local hour. Unknown or missing status is not counted as occupied; one primary provider is selected per station to avoid duplicate provider mappings.","provider_uids":["eround"],"requested_days":7,"start_date":"2026-05-09","station":{"address":"Karl-Friedrich-Straße 97 79312 Emmendingen Landkreis Emmendingen","charging_points_count":2,"city":"Emmendingen","max_power_kw":150.0,"operator":"Pfalzwerke AG","postcode":"79312","station_id":"0bbaf7a2d7bd3c3b"},"station_id":"0bbaf7a2d7bd3c3b","timezone":"Europe/Berlin"}