{"end_date":"2026-05-14","hourly_average_occupied":{"00:00":0.062,"01:00":0.123,"02:00":0.0,"03:00":0.046,"04:00":0.04,"05:00":0.0,"06:00":0.167,"07:00":0.277,"08:00":1.26,"09:00":2.65,"10:00":3.5,"11:00":3.484,"12:00":4.55,"13:00":4.18,"14:00":3.134,"15:00":3.698,"16:00":4.5,"17:00":4.686,"18:00":3.666,"19:00":3.425,"20:00":1.622,"21:00":0.245,"22:00":0.024,"23:00":0.024},"included_days":7,"metric":"Mean occupied EVSEs per local hour. Unknown or missing status is not counted as occupied; one primary provider is selected per station to avoid duplicate provider mappings.","provider_uids":["enbwmobility"],"requested_days":7,"start_date":"2026-05-08","station":{"address":"Jakob-Caspers-Str. 2 56070 Koblenz Kreisfreie Stadt Koblenz","charging_points_count":22,"city":"Koblenz","max_power_kw":300.0,"operator":"EnBW mobility+ AG und Co.KG","postcode":"56070","station_id":"173d4ef1938bc818"},"station_id":"173d4ef1938bc818","timezone":"Europe/Berlin"}