{"end_date":"2026-05-14","hourly_average_occupied":{"00:00":0.0,"01:00":0.0,"02:00":0.0,"03:00":0.0,"04:00":0.0,"05:00":0.0,"06:00":0.0,"07:00":0.133,"08:00":0.145,"09:00":0.377,"10:00":0.709,"11:00":0.617,"12:00":0.702,"13:00":1.0,"14:00":1.02,"15:00":1.252,"16:00":1.286,"17:00":1.286,"18:00":1.469,"19:00":1.654,"20:00":1.694,"21:00":1.804,"22:00":1.714,"23:00":1.714},"included_days":7,"metric":"Mean occupied EVSEs per local hour. Unknown or missing status is not counted as occupied; one primary provider is selected per station to avoid duplicate provider mappings.","provider_uids":["tesla"],"requested_days":7,"start_date":"2026-05-08","station":{"address":"Willy-Brandt-Allee 1 91301 Forchheim Landkreis Forchheim","charging_points_count":8,"city":"Forchheim","max_power_kw":250.0,"operator":"Tesla Germany GmbH","postcode":"91301","station_id":"186f23d9bef1a3fb"},"station_id":"186f23d9bef1a3fb","timezone":"Europe/Berlin"}