{"end_date":"2026-05-16","hourly_average_occupied":{"00:00":0.233,"01:00":0.917,"02:00":1.294,"03:00":1.301,"04:00":1.134,"05:00":1.566,"06:00":1.83,"07:00":1.441,"08:00":1.008,"09:00":1.72,"10:00":1.583,"11:00":1.653,"12:00":1.357,"13:00":1.186,"14:00":1.298,"15:00":1.225,"16:00":1.935,"17:00":1.663,"18:00":1.772,"19:00":2.042,"20:00":2.139,"21:00":2.35,"22:00":2.09,"23:00":1.519},"included_days":7,"metric":"Mean occupied EVSEs per local hour. Unknown or missing status is not counted as occupied; one primary provider is selected per station to avoid duplicate provider mappings.","provider_uids":["eco_movement"],"requested_days":7,"start_date":"2026-05-10","station":{"address":"Steilshooper Allee 55 22309 Hamburg Kreisfreie Stadt Hamburg","charging_points_count":4,"city":"Hamburg","max_power_kw":300.0,"operator":"Shell Deutschland GmbH","postcode":"22309","station_id":"6c3a7a95d7783109"},"station_id":"6c3a7a95d7783109","timezone":"Europe/Berlin"}