{"end_date":"2026-05-15","hourly_average_occupied":{"00:00":0.0,"01:00":0.0,"02:00":0.0,"03:00":0.0,"04:00":0.0,"05:00":0.0,"06:00":0.0,"07:00":0.017,"08:00":0.057,"09:00":0.033,"10:00":0.236,"11:00":0.417,"12:00":0.298,"13:00":0.191,"14:00":0.398,"15:00":0.538,"16:00":0.49,"17:00":0.431,"18:00":0.355,"19:00":0.157,"20:00":0.443,"21:00":0.221,"22:00":0.148,"23:00":0.055},"included_days":7,"metric":"Mean occupied EVSEs per local hour. Unknown or missing status is not counted as occupied; one primary provider is selected per station to avoid duplicate provider mappings.","provider_uids":["smatrics"],"requested_days":7,"start_date":"2026-05-09","station":{"address":"Außerhalb 7 55291 Saulheim Landkreis Alzey-Worms","charging_points_count":4,"city":"Saulheim","max_power_kw":400.0,"operator":"SMATRICS GmbH & Co KG","postcode":"55291","station_id":"8caa4cf3996c49dd"},"station_id":"8caa4cf3996c49dd","timezone":"Europe/Berlin"}