{"end_date":"2026-05-12","hourly_average_occupied":{"00:00":0.0,"01:00":0.0,"02:00":0.021,"03:00":0.073,"04:00":0.0,"05:00":0.086,"06:00":0.157,"07:00":0.048,"08:00":0.416,"09:00":0.399,"10:00":0.306,"11:00":0.851,"12:00":0.825,"13:00":0.729,"14:00":0.713,"15:00":1.051,"16:00":0.78,"17:00":0.489,"18:00":0.692,"19:00":0.564,"20:00":0.426,"21:00":0.164,"22:00":0.208,"23:00":0.06},"included_days":7,"metric":"Mean occupied EVSEs per local hour. Unknown or missing status is not counted as occupied; one primary provider is selected per station to avoid duplicate provider mappings.","provider_uids":["edri"],"requested_days":7,"start_date":"2026-05-06","station":{"address":"Raststätte Rhön West 0 97795 Schondra Landkreis Bad Kissingen","charging_points_count":2,"city":"Schondra","max_power_kw":50.0,"operator":"E.ON Drive Infrastructure GmbH","postcode":"97795","station_id":"98070cf47bb55471"},"station_id":"98070cf47bb55471","timezone":"Europe/Berlin"}