{"end_date":"2026-05-13","hourly_average_occupied":{"00:00":0.113,"01:00":0.802,"02:00":0.549,"03:00":0.291,"04:00":0.111,"05:00":0.177,"06:00":0.338,"07:00":0.85,"08:00":2.451,"09:00":3.881,"10:00":3.941,"11:00":4.948,"12:00":5.416,"13:00":5.836,"14:00":4.508,"15:00":6.03,"16:00":5.649,"17:00":7.025,"18:00":4.879,"19:00":4.227,"20:00":3.127,"21:00":3.644,"22:00":3.17,"23:00":2.303},"included_days":7,"metric":"Mean occupied EVSEs per local hour. Unknown or missing status is not counted as occupied; one primary provider is selected per station to avoid duplicate provider mappings.","provider_uids":["enbwmobility"],"requested_days":7,"start_date":"2026-05-07","station":{"address":"Keltenstraße 20 36043 Fulda Landkreis Fulda","charging_points_count":10,"city":"Fulda","max_power_kw":300.0,"operator":"EnBW mobility+ AG und Co.KG","postcode":"36043","station_id":"a92a681f9691602f"},"station_id":"a92a681f9691602f","timezone":"Europe/Berlin"}