{"end_date":"2026-05-16","hourly_average_occupied":{"00:00":0.0,"01:00":0.0,"02:00":0.0,"03:00":0.0,"04:00":0.0,"05:00":0.0,"06:00":0.0,"07:00":0.01,"08:00":0.003,"09:00":0.375,"10:00":0.915,"11:00":0.646,"12:00":0.652,"13:00":0.741,"14:00":0.664,"15:00":0.48,"16:00":0.543,"17:00":0.958,"18:00":0.252,"19:00":0.669,"20:00":0.316,"21:00":0.219,"22:00":0.0,"23:00":0.0},"included_days":7,"metric":"Mean occupied EVSEs per local hour. Unknown or missing status is not counted as occupied; one primary provider is selected per station to avoid duplicate provider mappings.","provider_uids":["enbwmobility"],"requested_days":7,"start_date":"2026-05-10","station":{"address":"Castroper Str. 270 44791 Bochum Kreisfreie Stadt Bochum","charging_points_count":4,"city":"Bochum","max_power_kw":200.0,"operator":"EnBW mobility+ AG und Co.KG","postcode":"44791","station_id":"a993f3e4039000ca"},"station_id":"a993f3e4039000ca","timezone":"Europe/Berlin"}