{"end_date":"2026-05-11","hourly_average_occupied":{"00:00":0.01,"01:00":0.058,"02:00":0.029,"03:00":0.039,"04:00":0.064,"05:00":0.069,"06:00":0.067,"07:00":0.23,"08:00":0.548,"09:00":0.725,"10:00":0.744,"11:00":1.623,"12:00":1.52,"13:00":1.156,"14:00":1.215,"15:00":1.594,"16:00":1.316,"17:00":1.09,"18:00":1.105,"19:00":0.885,"20:00":0.847,"21:00":0.727,"22:00":0.629,"23:00":0.0},"included_days":7,"metric":"Mean occupied EVSEs per local hour. Unknown or missing status is not counted as occupied; one primary provider is selected per station to avoid duplicate provider mappings.","provider_uids":["eco_movement"],"requested_days":7,"start_date":"2026-05-05","station":{"address":"Im Heidegrund Süd 3 06721 Osterfeld Landkreis Burgenlandkreis","charging_points_count":4,"city":"Osterfeld","max_power_kw":300.0,"operator":"TEAG Mobil GmbH","postcode":"06721","station_id":"a9e415aae8749ca2"},"station_id":"a9e415aae8749ca2","timezone":"Europe/Berlin"}