{"end_date":"2026-05-12","hourly_average_occupied":{"00:00":0.0,"01:00":0.071,"02:00":0.0,"03:00":0.0,"04:00":0.0,"05:00":0.06,"06:00":0.155,"07:00":0.401,"08:00":0.342,"09:00":0.281,"10:00":0.325,"11:00":0.437,"12:00":0.381,"13:00":0.276,"14:00":0.239,"15:00":0.554,"16:00":0.635,"17:00":0.463,"18:00":0.418,"19:00":0.344,"20:00":0.021,"21:00":0.061,"22:00":0.039,"23:00":0.025},"included_days":7,"metric":"Mean occupied EVSEs per local hour. Unknown or missing status is not counted as occupied; one primary provider is selected per station to avoid duplicate provider mappings.","provider_uids":["vaylens"],"requested_days":7,"start_date":"2026-05-06","station":{"address":"Floßwörthstraße 49-55 68199 Mannheim Stadtkreis Mannheim","charging_points_count":3,"city":"Mannheim","max_power_kw":150.0,"operator":"ALDI SÜD Immobilienverwaltungs-GmbH & Co. oHG","postcode":"68199","station_id":"c0333912f431c853"},"station_id":"c0333912f431c853","timezone":"Europe/Berlin"}