{"end_date":"2026-05-14","hourly_average_occupied":{"00:00":0.044,"01:00":0.057,"02:00":0.0,"03:00":0.0,"04:00":0.0,"05:00":0.0,"06:00":0.088,"07:00":0.296,"08:00":0.476,"09:00":0.291,"10:00":0.526,"11:00":0.714,"12:00":1.039,"13:00":0.967,"14:00":0.738,"15:00":0.898,"16:00":0.636,"17:00":0.4,"18:00":0.844,"19:00":0.759,"20:00":0.412,"21:00":0.512,"22:00":0.412,"23:00":0.502},"included_days":7,"metric":"Mean occupied EVSEs per local hour. Unknown or missing status is not counted as occupied; one primary provider is selected per station to avoid duplicate provider mappings.","provider_uids":["edri"],"requested_days":7,"start_date":"2026-05-08","station":{"address":"Raststätte Leipheim Süd 0 89340 Leipheim Landkreis Günzburg","charging_points_count":2,"city":"Leipheim","max_power_kw":50.0,"operator":"E.ON Drive Infrastructure GmbH","postcode":"89340","station_id":"d6376e01bf3a1a59"},"station_id":"d6376e01bf3a1a59","timezone":"Europe/Berlin"}