{"end_date":"2026-05-11","hourly_average_occupied":{"00:00":0.001,"01:00":0.0,"02:00":0.047,"03:00":0.0,"04:00":0.0,"05:00":0.0,"06:00":0.031,"07:00":0.068,"08:00":0.432,"09:00":0.594,"10:00":0.847,"11:00":0.87,"12:00":0.566,"13:00":0.697,"14:00":0.853,"15:00":0.647,"16:00":0.905,"17:00":0.962,"18:00":0.991,"19:00":0.748,"20:00":0.753,"21:00":0.474,"22:00":0.362,"23:00":0.201},"included_days":7,"metric":"Mean occupied EVSEs per local hour. Unknown or missing status is not counted as occupied; one primary provider is selected per station to avoid duplicate provider mappings.","provider_uids":["eround"],"requested_days":7,"start_date":"2026-05-05","station":{"address":"Bockhorner Weg 7 29683 Bad Fallingbostel Landkreis Heidekreis","charging_points_count":2,"city":"Bad Fallingbostel","max_power_kw":300.0,"operator":"EWE Go GmbH","postcode":"29683","station_id":"e1036dae496257f3"},"station_id":"e1036dae496257f3","timezone":"Europe/Berlin"}