{"end_date":"2026-05-16","hourly_average_occupied":{"00:00":0.133,"01:00":0.654,"02:00":0.345,"03:00":0.294,"04:00":0.656,"05:00":0.756,"06:00":0.738,"07:00":1.426,"08:00":1.26,"09:00":2.194,"10:00":3.549,"11:00":3.686,"12:00":4.372,"13:00":4.289,"14:00":3.23,"15:00":2.683,"16:00":3.236,"17:00":3.672,"18:00":3.0,"19:00":2.096,"20:00":1.104,"21:00":1.109,"22:00":0.836,"23:00":0.962},"included_days":7,"metric":"Mean occupied EVSEs per local hour. Unknown or missing status is not counted as occupied; one primary provider is selected per station to avoid duplicate provider mappings.","provider_uids":["enbwmobility"],"requested_days":7,"start_date":"2026-05-10","station":{"address":"Albert-Einstein-Straße 1 34277 Fuldabrück Landkreis Kassel","charging_points_count":8,"city":"Fuldabrück","max_power_kw":300.0,"operator":"EnBW mobility+ AG und Co.KG","postcode":"34277","station_id":"e1eb9e6e6fc82e59"},"station_id":"e1eb9e6e6fc82e59","timezone":"Europe/Berlin"}